CHANGES.rst
LICENSE
MANIFEST.in
README.rst
demo.py
requirements.txt
setup.py
simpledemo.py
pythontop40/__init__.py
pythontop40/errors.py
pythontop40/package_info.json
pythontop40/top40.py
pythontop40.egg-info/PKG-INFO
pythontop40.egg-info/SOURCES.txt
pythontop40.egg-info/dependency_links.txt
pythontop40.egg-info/requires.txt
pythontop40.egg-info/top_level.txt