Metadata-Version: 1.1
Name: pythontop40
Version: 0.1.5
Summary: A Python API to access the UK Top 40 album and single charts (Intended to be used as a teaching aid in UK schools)
Home-page: https://bitbucket.org/dannygoodall/pythontop40
Author: Danny Goodall
Author-email: danny@onebloke.com
License: Apache v2.0
Platform: UNKNOWN
Classifier: Development Status :: 3 - Alpha
Classifier: Intended Audience :: Developers
Classifier: Natural Language :: English
Classifier: Operating System :: OS Independent
Classifier: Programming Language :: Python :: 2.7
Classifier: Programming Language :: Python :: 3.3
Classifier: Programming Language :: Python :: 3.4
Classifier: Topic :: Software Development :: Libraries :: Python Modules
